istsa-1.0.5.dist-info/licenses/LICENSE.txt
itsa/tsanalysis.py
itsa/gts/Gts.py
itsa/gts/__init__.py
itsa/gts/errors.py
itsa/gts/lib/__init__.py
itsa/gts/lib/analysis.py
itsa/gts/lib/outliers.py
itsa/gts/lib/format/F3pos.py
itsa/gts/lib/format/GMODfiles.py
itsa/gts/lib/format/GXpos.py
itsa/gts/lib/format/NGLtxyz.py
itsa/gts/lib/format/PBOpos.py
itsa/gts/lib/format/__init__.py
itsa/gts/lib/format/read_pos.py
itsa/gts/lib/frame/__init__.py
itsa/gts/lib/frame/euler_pole.py
itsa/gts/lib/frame/fixed_plate.py
itsa/gts/lib/frame/itrf_convert.py
itsa/gts/lib/primitive/__init__.py
itsa/gts/lib/primitive/check_gts.py
itsa/gts/lib/primitive/coordinates.py
itsa/gts/lib/primitive/copy.py
itsa/gts/lib/primitive/plot.py
itsa/gts/lib/primitive/select.py
itsa/gts/lib/primitive/time.py
itsa/gts/lib/primitive/velocity.py
itsa/jps/Jps.py
itsa/jps/__init__.py
itsa/jps/errors.py
itsa/jps/lib/__init__.py
itsa/jps/lib/check_jps.py
itsa/jps/lib/copy.py
itsa/jps/lib/fill_jps.py
itsa/jps/lib/select.py
itsa/jps/lib/write_jps.py
itsa/lib/Glinalg.py
itsa/lib/Green_functions.py
itsa/lib/__init__.py
itsa/lib/astrotime.py
itsa/lib/coordinates.py
itsa/lib/coords2iso3.py
itsa/lib/euler.py
itsa/lib/find_format.py
itsa/lib/format.py
itsa/lib/index_dates.py
itsa/lib/logfiles.py
itsa/lib/midas.py
itsa/lib/modif_vartype.py
itsa/lib/read_cat.py
itsa/lib/save_Gts_byproduct.py
itsa/lib/select_ev.py
istsa-1.0.5.dist-info/METADATA
istsa-1.0.5.dist-info/WHEEL
istsa-1.0.5.dist-info/top_level.txt
istsa-1.0.5.dist-info/RECORD
